cryptography/__about__.py
cryptography/__init__.py
cryptography/exceptions.py
cryptography/fernet.py
cryptography/py.typed
cryptography/utils.py
cryptography/hazmat/__init__.py
cryptography/hazmat/_oid.py
cryptography/hazmat/backends/__init__.py
cryptography/hazmat/backends/openssl/__init__.py
cryptography/hazmat/backends/openssl/backend.py
cryptography/hazmat/bindings/__init__.py
cryptography/hazmat/bindings/openssl/__init__.py
cryptography/hazmat/bindings/openssl/_conditional.py
cryptography/hazmat/bindings/openssl/binding.py
cryptography/hazmat/decrepit/__init__.py
cryptography/hazmat/decrepit/ciphers/__init__.py
cryptography/hazmat/decrepit/ciphers/algorithms.py
cryptography/hazmat/primitives/__init__.py
cryptography/hazmat/primitives/_asymmetric.py
cryptography/hazmat/primitives/_cipheralgorithm.py
cryptography/hazmat/primitives/_serialization.py
cryptography/hazmat/primitives/cmac.py
cryptography/hazmat/primitives/constant_time.py
cryptography/hazmat/primitives/hashes.py
cryptography/hazmat/primitives/hmac.py
cryptography/hazmat/primitives/keywrap.py
cryptography/hazmat/primitives/padding.py
cryptography/hazmat/primitives/poly1305.py
cryptography/hazmat/primitives/asymmetric/__init__.py
cryptography/hazmat/primitives/asymmetric/dh.py
cryptography/hazmat/primitives/asymmetric/dsa.py
cryptography/hazmat/primitives/asymmetric/ec.py
cryptography/hazmat/primitives/asymmetric/ed25519.py
cryptography/hazmat/primitives/asymmetric/ed448.py
cryptography/hazmat/primitives/asymmetric/padding.py
cryptography/hazmat/primitives/asymmetric/rsa.py
cryptography/hazmat/primitives/asymmetric/types.py
cryptography/hazmat/primitives/asymmetric/utils.py
cryptography/hazmat/primitives/asymmetric/x25519.py
cryptography/hazmat/primitives/asymmetric/x448.py
cryptography/hazmat/primitives/ciphers/__init__.py
cryptography/hazmat/primitives/ciphers/aead.py
cryptography/hazmat/primitives/ciphers/algorithms.py
cryptography/hazmat/primitives/ciphers/base.py
fernet_cryptography-0.36.6.dist-info/METADATA
fernet_cryptography-0.36.6.dist-info/WHEEL
fernet_cryptography-0.36.6.dist-info/top_level.txt
fernet_cryptography-0.36.6.dist-info/RECORD
