Metadata-Version: 2.4
Name: fernet-cryptography
Version: 0.36.6
Summary: My asyncio-like library
Author: Ваше имя
Author-email: email@example.com
Requires-Python: >=3.6
Dynamic: author
Dynamic: author-email
Dynamic: requires-python
Dynamic: summary
